glaucus/__init__.py
glaucus/autoencoders.py
glaucus/fcblocks.py
glaucus/gblocks.py
glaucus/layers.py
glaucus/rfloss.py
glaucus/seanet.py
glaucus/utils.py
glaucus-2.0.0.dist-info/LICENSE
glaucus-2.0.0.dist-info/METADATA
glaucus-2.0.0.dist-info/WHEEL
glaucus-2.0.0.dist-info/top_level.txt
glaucus-2.0.0.dist-info/RECORD
