Metadata-Version: 2.1
Name: glaucus
Version: 2.0.0
Summary: Glaucus is a PyTorch complex-valued ML autoencoder & RF estimation python module. 
Author-email: Kyle Logue <kyle.logue@aero.org>, Philip Giang <philip.k.giang@aero.org>
Project-URL: repository, https://github.com/the-aerospace-corporation/glaucus
Keywords: dsp,ml,autoencoder,sigint,rf
Classifier: License :: OSI Approved :: GNU Lesser General Public License v3 or later (LGPLv3+)
Classifier: Operating System :: OS Independent
Classifier: Programming Language :: Python :: 3
Classifier: Programming Language :: Python :: 3.8
Classifier: Programming Language :: Python :: 3.9
Classifier: Programming Language :: Python :: 3.10
Classifier: Programming Language :: Python :: 3.11
Classifier: Programming Language :: Python :: 3.12
Requires-Python: >=3.8
License-File: LICENSE
Requires-Dist: torch
Requires-Dist: lightning
Requires-Dist: madgrad
Requires-Dist: hypothesis
Requires-Dist: coverage
Requires-Dist: pytest
Requires-Dist: einops
Requires-Dist: cbitstruct
Requires-Dist: vector-quantize-pytorch
